Metadata-Version: 2.1
Name: phlcensus
Version: 0.0.6
Summary: Wrangling Census data for the City of Philadelphia
Home-page: UNKNOWN
Author: Nick Hand
Maintainer: Nick Hand
Maintainer-email: nick.hand@phila.gov
License: MIT
Platform: UNKNOWN
Requires-Python: >=3.6
Provides-Extra: dev
